flask_jobs/__init__.py
flask_jobs/cron.py
flask_jobs/flask_jobs_blueprint.py
flask_jobs/jobs.py
flask_jobs/worker.py
flask_jobs-1.0.14.dist-info/METADATA
flask_jobs-1.0.14.dist-info/WHEEL
flask_jobs-1.0.14.dist-info/top_level.txt
flask_jobs-1.0.14.dist-info/RECORD
