Metadata-Version: 2.1
Name: flask-jobs
Version: 1.0.14
Summary: An easy job scheduling interface for flask projects.
Home-page: https://github.com/GrantGMiller/flask_jobs
Author: Grant miller
Author-email: grant@grant-miller.com
License: PSF
Project-URL: Source Code, https://github.com/GrantGMiller/flask_jobs
Keywords: flask job scheduler apscheduler celery redis crontab cron job
Platform: UNKNOWN
Requires-Dist: flask-dictabase
Requires-Dist: python-crontab
